{"bibleAbbr":"KJPCE1900+","bookName":"Job","bookEnglishName":"Job","chapterNumber":1,"verses":[{"number":1,"verse":"There was a man <S%H376><s%> in the land <S%H776><s%> of Uz <S%H5780><s%>, whose name <S%H8034><s%> was Job <S%H347><s%>; and that man <S%H376><s%> was perfect <S%H8535><s%> and upright <S%H3477><s%>, and one that feared <S%H3373><s%> God <S%H430><s%>, and eschewed <S%H5493><s%> evil <S%H7451><s%>."},{"number":2,"verse":"And there were born <S%H3205><s%> unto him seven <S%H7651><s%> sons <S%H1121><s%> and three <S%H7969><s%> daughters <S%H1323><s%>."},{"number":3,"verse":"His substance <S%H4735><s%> also was seven <S%H7651><s%> thousand <S%H505><s%> sheep <S%H6629><s%>, and three <S%H7969><s%> thousand <S%H505><s%> camels <S%H1581><s%>, and five <S%H2568><s%> hundred <S%H3967><s%> yoke <S%H6776><s%> of oxen <S%H1241><s%>, and five <S%H2568><s%> hundred <S%H3967><s%> she asses <S%H860><s%>, and a very <S%H3966><s%> great <S%H7227><s%> household <S%H5657><s%>; so that this man <S%H376><s%> was the greatest <S%H1419><s%> of all the men <S%H1121><s%> of the east <S%H6924><s%>."},{"number":4,"verse":"And his sons <S%H1121><s%> went <S%H1980><s%> and feasted <S%H4960><s%> <S%H6213><s%> in their houses <S%H1004><s%>, every one <S%H376><s%> his day <S%H3117><s%>; and sent <S%H7971><s%> and called <S%H7121><s%> for their three <S%H7969><s%> sisters <S%H269><s%> to eat <S%H398><s%> and to drink <S%H8354><s%> with them."},{"number":5,"verse":"And it was so, when the days <S%H3117><s%> of their feasting <S%H4960><s%> were gone about <S%H5362><s%>, that Job <S%H347><s%> sent <S%H7971><s%> and sanctified <S%H6942><s%> them, and rose up early <S%H7925><s%> in the morning <S%H1242><s%>, and offered <S%H5927><s%> burnt offerings <S%H5930><s%> according to the number <S%H4557><s%> of them all: for Job <S%H347><s%> said <S%H559><s%>, It may be <S%H194><s%> that my sons <S%H1121><s%> have sinned <S%H2398><s%>, and cursed <S%H1288><s%> God <S%H430><s%> in their hearts <S%H3824><s%>. Thus did <S%H6213><s%> Job <S%H347><s%> continually <S%H3117><s%>."},{"number":6,"verse":"¶ Now there was a day <S%H3117><s%> when the sons <S%H1121><s%> of God <S%H430><s%> came <S%H935><s%> to present <S%H3320><s%> themselves before the LORD <S%H3068><s%>, and Satan <S%H7854><s%> came <S%H935><s%> also among <S%H8432><s%> them."},{"number":7,"verse":"And the LORD <S%H3068><s%> said <S%H559><s%> unto Satan <S%H7854><s%>, Whence <S%H370><s%> comest <S%H935><s%> thou? Then Satan <S%H7854><s%> answered <S%H6030><s%> the LORD <S%H3068><s%>, and said <S%H559><s%>, From going to and fro <S%H7751><s%> in the earth <S%H776><s%>, and from walking up and down <S%H1980><s%> in it."},{"number":8,"verse":"And the LORD <S%H3068><s%> said <S%H559><s%> unto Satan <S%H7854><s%>, Hast thou considered <S%H7760><s%> <S%H3820><s%> my servant <S%H5650><s%> Job <S%H347><s%>, that there is none like him in the earth <S%H776><s%>, a perfect <S%H8535><s%> and an upright <S%H3477><s%> man <S%H376><s%>, one that feareth <S%H3373><s%> God <S%H430><s%>, and escheweth <S%H5493><s%> evil <S%H7451><s%>?"},{"number":9,"verse":"Then Satan <S%H7854><s%> answered <S%H6030><s%> the LORD <S%H3068><s%>, and said <S%H559><s%>, Doth Job <S%H347><s%> fear <S%H3372><s%> God <S%H430><s%> for nought <S%H2600><s%>?"},{"number":10,"verse":"Hast not thou made an hedge <S%H7753><s%> about him, and about <S%H1157><s%> his house <S%H1004><s%>, and about all that he hath on every side <S%H5439><s%>? thou hast blessed <S%H1288><s%> the work <S%H4639><s%> of his hands <S%H3027><s%>, and his substance <S%H4735><s%> is increased <S%H6555><s%> in the land <S%H776><s%>."},{"number":11,"verse":"But <S%H199><s%> put forth <S%H7971><s%> thine hand <S%H3027><s%> now, and touch <S%H5060><s%> all that he hath, and he will curse <S%H1288><s%> <S%H3808><s%> thee to thy face <S%H6440><s%>."},{"number":12,"verse":"And the LORD <S%H3068><s%> said <S%H559><s%> unto Satan <S%H7854><s%>, Behold, all that he hath is in thy power <S%H3027><s%>; only upon himself put not forth <S%H7971><s%> thine hand <S%H3027><s%>. So Satan <S%H7854><s%> went forth <S%H3318><s%> from the presence <S%H6440><s%> of the LORD <S%H3068><s%>."},{"number":13,"verse":"¶ And there was a day <S%H3117><s%> when his sons <S%H1121><s%> and his daughters <S%H1323><s%> were eating <S%H398><s%> and drinking <S%H8354><s%> wine <S%H3196><s%> in their eldest <S%H1060><s%> brother's <S%H251><s%> house <S%H1004><s%>:"},{"number":14,"verse":"And there came <S%H935><s%> a messenger <S%H4397><s%> unto Job <S%H347><s%>, and said <S%H559><s%>, The oxen <S%H1241><s%> were plowing <S%H2790><s%>, and the asses <S%H860><s%> feeding <S%H7462><s%> beside <S%H3027><s%> them:"},{"number":15,"verse":"And the Sabeans <S%H7614><s%> fell <S%H5307><s%> upon them, and took them away <S%H3947><s%>; yea, they have slain <S%H5221><s%> the servants <S%H5288><s%> with the edge <S%H6310><s%> of the sword <S%H2719><s%>; and I only am escaped <S%H4422><s%> alone to tell <S%H5046><s%> thee."},{"number":16,"verse":"While he was yet speaking <S%H1696><s%>, there came <S%H935><s%> also another, and said <S%H559><s%>, The fire <S%H784><s%> of God <S%H430><s%> is fallen <S%H5307><s%> from heaven <S%H8064><s%>, and hath burned up <S%H1197><s%> the sheep <S%H6629><s%>, and the servants <S%H5288><s%>, and consumed <S%H398><s%> them; and I only am escaped <S%H4422><s%> alone to tell <S%H5046><s%> thee."},{"number":17,"verse":"While he was yet speaking <S%H1696><s%>, there came <S%H935><s%> also another, and said <S%H559><s%>, The Chaldeans <S%H3778><s%> made out <S%H7760><s%> three <S%H7969><s%> bands <S%H7218><s%>, and fell <S%H6584><s%> upon the camels <S%H1581><s%>, and have carried them away <S%H3947><s%>, yea, and slain <S%H5221><s%> the servants <S%H5288><s%> with the edge <S%H6310><s%> of the sword <S%H2719><s%>; and I only am escaped <S%H4422><s%> alone to tell <S%H5046><s%> thee."},{"number":18,"verse":"While he was yet speaking <S%H1696><s%>, there came <S%H935><s%> also another, and said <S%H559><s%>, Thy sons <S%H1121><s%> and thy daughters <S%H1323><s%> were eating <S%H398><s%> and drinking <S%H8354><s%> wine <S%H3196><s%> in their eldest <S%H1060><s%> brother's <S%H251><s%> house <S%H1004><s%>:"},{"number":19,"verse":"And, behold, there came <S%H935><s%> a great <S%H1419><s%> wind <S%H7307><s%> from <S%H5676><s%> the wilderness <S%H4057><s%>, and smote <S%H5060><s%> the four <S%H702><s%> corners <S%H6438><s%> of the house <S%H1004><s%>, and it fell <S%H5307><s%> upon the young men <S%H5288><s%>, and they are dead <S%H4191><s%>; and I only am escaped <S%H4422><s%> alone to tell <S%H5046><s%> thee."},{"number":20,"verse":"Then Job <S%H347><s%> arose <S%H6965><s%>, and rent <S%H7167><s%> his mantle <S%H4598><s%>, and shaved <S%H1494><s%> his head <S%H7218><s%>, and fell down <S%H5307><s%> upon the ground <S%H776><s%>, and worshipped <S%H7812><s%>,"},{"number":21,"verse":"And said <S%H559><s%>, Naked <S%H6174><s%> came I out <S%H3318><s%> of my mother's <S%H517><s%> womb <S%H990><s%>, and naked <S%H6174><s%> shall I return <S%H7725><s%> thither: the LORD <S%H3068><s%> gave <S%H5414><s%>, and the LORD <S%H3068><s%> hath taken away <S%H3947><s%>; blessed <S%H1288><s%> be the name <S%H8034><s%> of the LORD <S%H3068><s%>."},{"number":22,"verse":"In all this Job <S%H347><s%> sinned <S%H2398><s%> not, nor charged <S%H5414><s%> God <S%H430><s%> foolishly <S%H8604><s%>."}]}