{"bibleAbbr":"cKJV+","bookName":"Deuteronomy","bookEnglishName":"Deuteronomy","chapterNumber":20,"verses":[{"number":1,"verse":"When you go out <S%H3318><s%> to battle <S%H4421><s%> against your enemies <S%H341><s%>, and see <S%H7200><s%> horses <S%H5483><s%>, and chariots <S%H7393><s%>, and a people <S%H5971><s%> more <S%H7227><s%> than you <S%H3372><s%>, be not afraid of them <S%H3068><s%>: for the Lord your God <S%H430><s%> is with you <S%H5927><s%>, which brought you up out of the land <S%H776><s%> of Egypt <S%H4714><s%>."},{"number":2,"verse":"And it shall be <S%H7126><s%>, when you are come near unto the battle <S%H4421><s%>, that the priest <S%H3548><s%> shall approach <S%H5066><s%> and speak <S%H1696><s%> unto the people <S%H5971><s%>,"},{"number":3,"verse":"And shall say <S%H559><s%> unto them <S%H8085><s%>, Hear, O Israel <S%H3478><s%>, you approach <S%H7131><s%> this day <S%H3117><s%> unto battle <S%H4421><s%> against your enemies <S%H341><s%>: let not your hearts <S%H3824><s%> faint <S%H7401><s%>, fear <S%H3372><s%> not <S%H2648><s%>, and do not tremble, neither be you terrified <S%H6206><s%> because of them <S%H6440><s%>;"},{"number":4,"verse":"For the Lord <S%H3068><s%> your God <S%H430><s%> is he that goes <S%H1980><s%> with you <S%H3898><s%>, to fight for you against your enemies <S%H341><s%>, to save you <S%H3467><s%>."},{"number":5,"verse":"And the officers <S%H7860><s%> shall speak <S%H1696><s%> unto the people <S%H5971><s%>, saying <S%H559><s%>, What man <S%H376><s%> is there that has built <S%H1129><s%> a new <S%H2319><s%> house <S%H1004><s%>, and has not dedicated <S%H2596><s%> it <S%H3212><s%>? let him go and return <S%H7725><s%> to his house <S%H1004><s%>, lest he die <S%H4191><s%> in the battle <S%H4421><s%>, and another <S%H312><s%> man <S%H376><s%> dedicate it <S%H2596><s%>."},{"number":6,"verse":"And what man <S%H376><s%> is he that has planted <S%H5193><s%> a vineyard <S%H3754><s%>, and has not yet eaten <S%H2490><s%> of it <S%H3212><s%>? let him also go and return <S%H7725><s%> unto his house <S%H1004><s%>, lest he die <S%H4191><s%> in the battle <S%H4421><s%>, and another <S%H312><s%> man <S%H376><s%> eat of it <S%H2490><s%>."},{"number":7,"verse":"And what man <S%H376><s%> is there that has married <S%H781><s%> a wife <S%H802><s%>, and has not taken <S%H3947><s%> her <S%H3212><s%>? let him go and return <S%H7725><s%> unto his house <S%H1004><s%>, lest he die <S%H4191><s%> in the battle <S%H4421><s%>, and another <S%H312><s%> man <S%H376><s%> take her <S%H3947><s%>."},{"number":8,"verse":"And the officers <S%H7860><s%> shall speak <S%H1696><s%> further <S%H3254><s%> unto the people <S%H5971><s%>, and they shall say <S%H559><s%>, What man <S%H376><s%> is there that is fearful <S%H3373><s%> and fainthearted <S%H7390><s%>? let him go <S%H3212><s%> and return <S%H7725><s%> unto his house <S%H1004><s%>, lest his brothers <S%H251><s%> heart <S%H3824><s%> faint <S%H4549><s%> as well as his heart <S%H3824><s%>."},{"number":9,"verse":"And it shall be <S%H7860><s%>, when the officers have made an end <S%H3615><s%> of speaking <S%H1696><s%> unto the people <S%H5971><s%>, that they shall make <S%H6485><s%> captains <S%H8269><s%> of the armies <S%H6635><s%> to lead <S%H7218><s%> the people <S%H5971><s%>."},{"number":10,"verse":"When you come near <S%H7126><s%> unto a city <S%H5892><s%> to fight <S%H3898><s%> against it <S%H7121><s%>, then proclaim peace unto it <S%H7965><s%>."},{"number":11,"verse":"And it shall be <S%H6030><s%>, if it make you answer of peace <S%H7965><s%>, and open <S%H6605><s%> unto you <S%H5971><s%>, then it shall be, that all the people that is found <S%H4672><s%> in it shall be tributaries <S%H4522><s%> unto you <S%H5647><s%>, and they shall serve you."},{"number":12,"verse":"And if it will make no peace <S%H7999><s%> with you <S%H6213><s%>, but will make war <S%H4421><s%> against you <S%H6696><s%>, then you shall besiege it:"},{"number":13,"verse":"And when the Lord <S%H3068><s%> your God <S%H430><s%> has delivered <S%H5414><s%> it into your hands <S%H3027><s%>, you shall strike <S%H5221><s%> every male <S%H2138><s%> there with the edge <S%H6310><s%> of the sword <S%H2719><s%>:"},{"number":14,"verse":"But the women <S%H802><s%>, and the little ones <S%H2945><s%>, and the cattle <S%H929><s%>, and all that is in the city <S%H5892><s%>, even all the plunder <S%H7998><s%> there <S%H962><s%>, shall you take unto yourself <S%H398><s%>; and you shall eat the plunder <S%H7998><s%> of your enemies <S%H341><s%>, which the Lord <S%H3068><s%> your God <S%H430><s%> has given you <S%H5414><s%>."},{"number":15,"verse":"Thus shall you do <S%H6213><s%> unto all the cities <S%H5892><s%> which are very <S%H3966><s%> far off <S%H7350><s%> from you <S%H2007><s%>, which are not of the cities <S%H5892><s%> of these nations <S%H1471><s%>."},{"number":16,"verse":"But of the cities <S%H5892><s%> of these people <S%H5971><s%>, which the Lord <S%H3068><s%> your God <S%H430><s%> does give <S%H5414><s%> you for an inheritance <S%H5159><s%>, you shall save alive <S%H2421><s%> nothing that breathes <S%H5397><s%>:"},{"number":17,"verse":"But you shall utterly <S%H2763><s%> destroy <S%H2763><s%> them <S%H2850><s%>; namely, the Hittites, and the Amorites <S%H567><s%>, the Canaanites <S%H3669><s%>, and the Perizzites <S%H6522><s%>, the Hivites <S%H2340><s%>, and the Jebusites <S%H2983><s%>; as the Lord <S%H3068><s%> your God <S%H430><s%> has commanded you <S%H6680><s%>:"},{"number":18,"verse":"That they teach <S%H3925><s%> you not to do <S%H6213><s%> after all their abominations <S%H8441><s%>, which they have done <S%H6213><s%> unto their gods <S%H430><s%>; so should you sin <S%H2398><s%> against the Lord <S%H3068><s%> your God <S%H430><s%>."},{"number":19,"verse":"When you shall besiege <S%H6696><s%> a city <S%H5892><s%> a long <S%H7227><s%> time <S%H3117><s%>, in making war <S%H3898><s%> against it to take <S%H8610><s%> it <S%H7843><s%>, you shall not destroy the trees <S%H6086><s%> there by wielding <S%H5080><s%> an axe <S%H1631><s%> against them <S%H398><s%>: for you may eat of them <S%H3772><s%>, and you shall not cut them down (for the tree <S%H6086><s%> of the field <S%H7704><s%> is man <S%H120><s%>'s life <S%H935><s%>) to employ them in the siege <S%H6440><s%>:"},{"number":20,"verse":"Only the trees <S%H6086><s%> which you know <S%H3045><s%> that they be not trees <S%H6086><s%> for food <S%H3978><s%>, you shall destroy <S%H7843><s%> and cut them down <S%H3772><s%>; and you shall build <S%H1129><s%> bulwarks <S%H4692><s%> against the city <S%H5892><s%> that makes <S%H6213><s%> war <S%H4421><s%> with you <S%H3381><s%>, until it be subdued."}]}