{"bibleAbbr":"NASB1995+","bookName":"Matthew","bookEnglishName":"Matthew","chapterNumber":3,"verses":[{"number":1,"verse":"Now <WG1161> in those <WG1565> days <WG2250> John <WG2491> the Baptist <WG910> came, <WG3854> preaching <WG2784> in the wilderness <WG2048> of Judea, <WG2453> saying, <WG3004>"},{"number":2,"verse":"\"Repent, <WG3340> for the kingdom <WG932> of heaven <WG3772> is at hand. <WG1448>\""},{"number":3,"verse":"For this <WG3778> is the one referred <WG3004> to by Isaiah <WG2268> the prophet, <WG4396> saying, <WG3004> \"The voice <WG5456> of one crying <WG994> in the wilderness, <WG2048> 'Make <WG2090> ready <WG2090> the way <WG3598> of the Lord, <WG2962> Make <WG4160> His paths <WG5147> straight! <WG2117>'\""},{"number":4,"verse":"Now <WG1161> John <WG2491> himself <WG846> had <WG2192> a garment <WG1742> of camel's hair, <WG2359> and a leather <WG1193> belt <WG2223> about <WG4012> his waist; <WG3751> and his food <WG5160> was locusts <WG200> and wild <WG66> honey. <WG3192>"},{"number":5,"verse":"Then <WG5119> Jerusalem <WG2414> was going <WG1607> out to him, and all <WG3956> Judea, <WG2453> and all <WG3956> the district <WG4066> around <WG4066> the Jordan; <WG2446>"},{"number":6,"verse":"and they were being baptized <WG907> by him in the Jordan <WG2446> River, <WG4215> as they confessed <WG1843> their sins. <WG266>"},{"number":7,"verse":"But when he saw <WG3708> many <WG4183> of the Pharisees <WG5330> and Sadducees <WG4523> coming <WG2064> for baptism, <WG908> he said <WG3004> to them, \"You brood <WG1081> of vipers, <WG2191> who <WG5101> warned <WG5263> you to flee <WG5343> from the wrath <WG3709> to come <WG3195>?"},{"number":8,"verse":"\"Therefore <WG3767> bring <WG4160> forth <WG4160> fruit <WG2590> in keeping <WG514> with repentance; <WG3341>"},{"number":9,"verse":"and do not suppose <WG1380> that you can say <WG3004> to yourselves, <WG1438> 'We have <WG2192> Abraham <WG11> for our father <WG3962>'; for I say <WG3004> to you, that God <WG2316> is able <WG1410> from these <WG3778> stones <WG3037> to raise <WG1453> up children <WG5043> to Abraham. <WG11>"},{"number":10,"verse":"\"And the axe <WG513> is already <WG2235> laid <WG2749> at the root <WG4491> of the trees; <WG1186> every <WG3956> tree <WG1186> therefore <WG3767> that does not bear <WG4160> good <WG2570> fruit <WG2590> is cut <WG1581> down <WG1581> and thrown <WG906> into the fire. <WG4442>"},{"number":11,"verse":"\"As for me, I baptize <WG907> you with water <WG5204> for repentance, <WG3341> but He who is coming <WG2064> after <WG3694> me is mightier <WG2478> than I, and I am <WG1510> not fit <WG2425> to remove <WG941> His sandals; <WG5266> He will baptize <WG907> you with the Holy <WG40> Spirit <WG4151> and fire. <WG4442>"},{"number":12,"verse":"\"And His winnowing <WG4425> fork <WG4425> is in His hand, <WG5495> and He will thoroughly <WG1245> clear <WG1245> His threshing <WG257> floor; <WG257> and He will gather <WG4863> His wheat <WG4621> into the barn, <WG596> but He will burn <WG2618> up the chaff <WG892> with unquenchable <WG762> fire. <WG4442>\""},{"number":13,"verse":"Then <WG5119> Jesus <WG2424> arrived <WG3854> from Galilee <WG1056> at the Jordan <WG2446> [coming] to John, <WG2491> to be baptized <WG907> by him."},{"number":14,"verse":"But John <WG2491> tried to prevent <WG1254> Him, saying, <WG3004> \"I have <WG2192> need <WG5532> to be baptized <WG907> by You, and do You come <WG2064> to me?\""},{"number":15,"verse":"But Jesus <WG2424> answering <WG611> said <WG3004> to him, \"Permit <WG863> [it] at this <WG737> time; <WG737> for in this <WG3779> way <WG3779> it is fitting <WG4241> for us to fulfill <WG4137> all <WG3956> righteousness. <WG1343>\" Then <WG5119> he permitted <WG863> Him."},{"number":16,"verse":"And after being baptized, <WG907> Jesus <WG2424> went <WG305> up immediately <WG2117> from the water; <WG5204> and behold, <WG2400> the heavens <WG3772> were opened, <WG455> and he saw <WG3708> the Spirit <WG4151> of God <WG2316> descending <WG2597> as a dove, <WG4058> [and] coming <WG2064> upon Him,"},{"number":17,"verse":"and behold, <WG2400> a voice <WG5456> out of the heavens, <WG3772> saying, <WG3004> \"This <WG3778> is My beloved <WG27> Son, <WG5207> in whom <WG3739> I am <WG2106> well-pleased.\""}]}