{"bibleAbbr":"NASB1995","bookName":"Matthew","bookEnglishName":"Matthew","chapterNumber":10,"verses":[{"number":1,"verse":"And having <S%G4341>summoned<s%> His <S%G1427>twelve<s%> <S%G3101>disciples,<s%> He <S%G1325>gave<s%> them <S%G1849>authority<s%> over <S%G169>unclean<s%> <S%G4151>spirits,<s%> to <S%G1544>cast<s%> them out, and to <S%G2323>heal<s%> <S%G3956>every<s%> <S%G3956>kind<s%> of <S%G3554>disease<s%> and <S%G3956>every<s%> <S%G3956>kind<s%> of <S%G3119>sickness.<s%>"},{"number":2,"verse":"<S%G1161>Now<s%> the <S%G3686>names<s%> of the <S%G1427>twelve<s%> <S%G652>apostles<s%> are <S%G3778>these:<s%> The <S%G4413>first,<s%> <S%G4613>Simon,<s%> who is <S%G3004>called<s%> <S%G4074>Peter,<s%> and <S%G406>Andrew<s%> his <S%G80>brother;<s%> and <S%G2385>James<s%> the [son] of <S%G2199>Zebedee,<s%> and <S%G2491>John<s%> his <S%G80>brother;<s%>"},{"number":3,"verse":"<S%G5376>Philip<s%> and <S%G918>Bartholomew;<s%> <S%G2381>Thomas<s%> and <S%G3102>Matthew<s%> the tax-gatherer; <S%G2385>James<s%> the [son] of <S%G256>Alphaeus,<s%> and <S%G2280>Thaddaeus;<s%>"},{"number":4,"verse":"<S%G4613>Simon<s%> the <S%G2581>Zealot,<s%> and <S%G2455>Judas<s%> <S%G2469>Iscariot,<s%> the one who <S%G3860>betrayed<s%> Him."},{"number":5,"verse":"<S%G3778>These<s%> <S%G1427>twelve<s%> <S%G2424>Jesus<s%> <S%G649>sent<s%> out after <S%G3853>instructing<s%> them, <S%G3004>saying,<s%> \"Do not <S%G565>go<s%> in [the] <S%G3598>way<s%> of [the] <S%G1484>Gentiles,<s%> and do not <S%G1525>enter<s%> [any] <S%G4172>city<s%> of the <S%G4541>Samaritans;<s%>"},{"number":6,"verse":"\"but <S%G3123>rather<s%> <S%G4198>go<s%> to the <S%G622>lost<s%> <S%G4263>sheep<s%> of the <S%G3624>house<s%> of <S%G2474>Israel.<s%>"},{"number":7,"verse":"\"And as you <S%G4198>go,<s%> <S%G2784>preach,<s%> <S%G3004>saying,<s%> 'The <S%G932>kingdom<s%> of <S%G3772>heaven<s%> is at <S%G1448>hand.<s%>'"},{"number":8,"verse":"<S%G2323>\"Heal<s%> [the] <S%G770>sick,<s%> <S%G1453>raise<s%> [the] <S%G3498>dead,<s%> <S%G2511>cleanse<s%> [the] <S%G3015>lepers,<s%> <S%G1544>cast<s%> out <S%G1140>demons;<s%> <S%G1432>freely<s%> you <S%G2983>received,<s%> <S%G1431>freely<s%> <S%G1325>give.<s%>"},{"number":9,"verse":"\"Do not <S%G2932>acquire<s%> <S%G5557>gold,<s%> <S%G3366>or<s%> <S%G696>silver,<s%> <S%G3366>or<s%> <S%G5475>copper<s%> for your <S%G5475>money<s%> <S%G2223>belts,<s%>"},{"number":10,"verse":"<S%G3361>or<s%> a <S%G4082>bag<s%> for [your] <S%G3598>journey,<s%> <S%G3366>or<s%> <S%G3366>even<s%> <S%G1417>two<s%> <S%G5509>tunics,<s%> <S%G3366>or<s%> <S%G5266>sandals,<s%> <S%G3366>or<s%> a <S%G4464>staff;<s%> for the <S%G2040>worker<s%> is <S%G514>worthy<s%> of his <S%G5160>support.<s%>"},{"number":11,"verse":"\"And into <S%G3739>whatever<s%> <S%G302><s%> <S%G4172>city<s%> <S%G2228>or<s%> <S%G2968>village<s%> you <S%G1525>enter,<s%> <S%G1833>inquire<s%> <S%G5101>who<s%> is <S%G514>worthy<s%> in it; and <S%G3306>abide<s%> <S%G2546>there<s%> <S%G2193>until<s%> you <S%G1831>go<s%> <S%G1831>away.<s%>"},{"number":12,"verse":"\"And as you <S%G1525>enter<s%> the <S%G3614>house,<s%> <S%G782>give<s%> it your <S%G782>greeting.<s%>"},{"number":13,"verse":"\"And <S%G1437>if<s%> the <S%G3614>house<s%> is <S%G514>worthy,<s%> let your [greeting of] <S%G1515>peace<s%> <S%G2064>come<s%> upon it; but <S%G1437>if<s%> it is not <S%G514>worthy,<s%> let your [greeting of] <S%G1515>peace<s%> <S%G1994>return<s%> to you."},{"number":14,"verse":"\"And <S%G3739>whoever<s%> <S%G1437><s%> does not <S%G1209>receive<s%> you, <S%G3366>nor<s%> <S%G191>heed<s%> your <S%G3056>words,<s%> as you <S%G1831>go<s%> out of that <S%G3614>house<s%> <S%G2228>or<s%> that <S%G4172>city,<s%> <S%G1621>shake<s%> <S%G1621>off<s%> the <S%G2868>dust<s%> of your <S%G4228>feet.<s%>"},{"number":15,"verse":"<S%G281>\"Truly<s%> I <S%G3004>say<s%> to you, it will be <S%G414>more<s%> <S%G414>tolerable<s%> for [the] <S%G1093>land<s%> of <S%G4670>Sodom<s%> and <S%G1116>Gomorrah<s%> in the <S%G2250>day<s%> of <S%G2920>judgment,<s%> <S%G2228>than<s%> for that <S%G4172>city.<s%>"},{"number":16,"verse":"<S%G2400>\"Behold,<s%> I <S%G649>send<s%> you out as <S%G4263>sheep<s%> in the <S%G3319>midst<s%> of <S%G3074>wolves;<s%> <S%G3767>therefore<s%> be <S%G5429>shrewd<s%> as <S%G3789>serpents,<s%> and <S%G185>innocent<s%> as <S%G4058>doves.<s%>"},{"number":17,"verse":"\"But <S%G4337>beware<s%> of <S%G444>men;<s%> for they will <S%G3860>deliver<s%> you up to [the] <S%G4892>courts,<s%> and <S%G3146>scourge<s%> you in their <S%G4864>synagogues;<s%>"},{"number":18,"verse":"and you shall <S%G2532>even<s%> be <S%G71>brought<s%> <S%G1909>before<s%> <S%G2232>governors<s%> and <S%G935>kings<s%> for My <S%G1752>sake,<s%> as a <S%G3142>testimony<s%> to them and to the <S%G1484>Gentiles.<s%>"},{"number":19,"verse":"\"But <S%G3752>when<s%> they <S%G3860>deliver<s%> you up, do not become <S%G3309>anxious<s%> about <S%G4459>how<s%> <S%G2228>or<s%> <S%G5101>what<s%> you will <S%G2980>speak;<s%> for it shall be <S%G1325>given<s%> you in that <S%G5610>hour<s%> <S%G5101>what<s%> you are to <S%G2980>speak.<s%>"},{"number":20,"verse":"\"For it is not you who <S%G2980>speak,<s%> but [it is] the <S%G4151>Spirit<s%> of your <S%G3962>Father<s%> who <S%G2980>speaks<s%> in you."},{"number":21,"verse":"\"And <S%G80>brother<s%> will <S%G3860>deliver<s%> up <S%G80>brother<s%> to <S%G2288>death,<s%> and a <S%G3962>father<s%> [his] <S%G5043>child;<s%> and <S%G5043>children<s%> will <S%G1881>rise<s%> up <S%G1909>against<s%> <S%G1118>parents,<s%> and <S%G2289>cause<s%> them to be <S%G2289>put<s%> to <S%G2289>death.<s%>"},{"number":22,"verse":"\"And you will be <S%G3404>hated<s%> by <S%G3956>all<s%> on <S%G1223>account<s%> of My <S%G3686>name,<s%> but it is the one who has <S%G5278>endured<s%> to the <S%G5056>end<s%> who will be <S%G4982>saved.<s%>"},{"number":23,"verse":"\"But <S%G3752>whenever<s%> they <S%G1377>persecute<s%> you in <S%G3778>this<s%> <S%G4172>city,<s%> <S%G5343>flee<s%> to the <S%G2087>next;<s%> for <S%G281>truly<s%> I <S%G3004>say<s%> to you, you shall not <S%G5055>finish<s%> [going through] the <S%G4172>cities<s%> of <S%G2474>Israel,<s%> <S%G2193>until<s%> the <S%G5207>Son<s%> of <S%G444>Man<s%> <S%G2064>comes.<s%>"},{"number":24,"verse":"\"A <S%G3101>disciple<s%> is not <S%G5228>above<s%> his <S%G1320>teacher,<s%> <S%G3761>nor<s%> a <S%G1401>slave<s%> <S%G5228>above<s%> his <S%G2962>master.<s%>"},{"number":25,"verse":"\"It is <S%G713>enough<s%> for the <S%G3101>disciple<s%> that he <S%G1096>become<s%> as his <S%G1320>teacher,<s%> and the <S%G1401>slave<s%> as his <S%G2962>master.<s%> <S%G1487>If<s%> they have <S%G1941>called<s%> the <S%G3617>head<s%> of the <S%G3617>house<s%> <S%G954>Beelzebul,<s%> <S%G4214>how<s%> <S%G4214>much<s%> <S%G3123>more<s%> the members of his <S%G3615>household!<s%>"},{"number":26,"verse":"<S%G3767>\"Therefore<s%> do not <S%G5399>fear<s%> them, for there is <S%G3762>nothing<s%> <S%G2572>covered<s%> that will not be <S%G601>revealed,<s%> and <S%G2927>hidden<s%> that will not be <S%G1097>known.<s%>"},{"number":27,"verse":"<S%G3739>\"What<s%> I <S%G3004>tell<s%> you in the <S%G4653>darkness,<s%> <S%G3004>speak<s%> in the <S%G5457>light;<s%> and <S%G3739>what<s%> you <S%G191>hear<s%> [whispered] in [your] <S%G3775>ear,<s%> <S%G2784>proclaim<s%> upon the <S%G1430>housetops.<s%>"},{"number":28,"verse":"\"And do not <S%G5399>fear<s%> <S%G3588>those<s%> who <S%G615>kill<s%> the <S%G4983>body,<s%> but are <S%G3361>unable<s%> <S%G1410><s%> to <S%G615>kill<s%> the <S%G5590>soul;<s%> but <S%G3123>rather<s%> <S%G5399>fear<s%> Him who is <S%G1410>able<s%> to <S%G622>destroy<s%> <S%G2532>both<s%> <S%G5590>soul<s%> and <S%G4983>body<s%> in <S%G1067>hell.<s%>"},{"number":29,"verse":"\"Are not <S%G1417>two<s%> <S%G4765>sparrows<s%> <S%G4453>sold<s%> for a <S%G787>cent<s%>? And [yet] not <S%G1520>one<s%> of them will <S%G4098>fall<s%> to the <S%G1093>ground<s%> <S%G427>apart<s%> from your <S%G3962>Father.<s%>"},{"number":30,"verse":"\"But the <S%G2532>very<s%> <S%G2359>hairs<s%> of your <S%G2776>head<s%> are <S%G3956>all<s%> <S%G705>numbered.<s%>"},{"number":31,"verse":"<S%G3767>\"Therefore<s%> do not <S%G5399>fear;<s%> you are of <S%G1308>more<s%> <S%G1308>value<s%> than <S%G4183>many<s%> <S%G4765>sparrows.<s%>"},{"number":32,"verse":"<S%G3956>\"Everyone<s%> <S%G3767>therefore<s%> <S%G3748>who<s%> shall <S%G3670>confess<s%> Me <S%G1715>before<s%> <S%G444>men,<s%> I will <S%G2532>also<s%> <S%G3670>confess<s%> him <S%G1715>before<s%> My <S%G3962>Father<s%> who is in <S%G3772>heaven.<s%>"},{"number":33,"verse":"\"But <S%G3748>whoever<s%> <S%G302><s%> shall <S%G720>deny<s%> Me <S%G1715>before<s%> <S%G444>men,<s%> I will <S%G2532>also<s%> <S%G720>deny<s%> him <S%G1715>before<s%> My <S%G3962>Father<s%> who is in <S%G3772>heaven.<s%>"},{"number":34,"verse":"\"Do not <S%G3543>think<s%> that I <S%G2064>came<s%> to <S%G906>bring<s%> <S%G1515>peace<s%> on the <S%G1093>earth;<s%> I did not <S%G2064>come<s%> to <S%G906>bring<s%> <S%G1515>peace,<s%> but a <S%G3162>sword.<s%>"},{"number":35,"verse":"\"For I <S%G2064>came<s%> to <S%G1369>set<s%> a <S%G444>man<s%> <S%G2596>against<s%> his <S%G3962>father,<s%> and a <S%G2364>daughter<s%> <S%G2596>against<s%> her <S%G3384>mother,<s%> and a daughter-in-law <S%G2596>against<s%> her mother-in-law;"},{"number":36,"verse":"and a man's <S%G2190>enemies<s%> will be the members of his <S%G3615>household.<s%>"},{"number":37,"verse":"\"He who <S%G5368>loves<s%> <S%G3962>father<s%> <S%G2228>or<s%> <S%G3384>mother<s%> <S%G5228>more<s%> <S%G5228>than<s%> Me is not <S%G514>worthy<s%> of Me; and he who <S%G5368>loves<s%> <S%G5207>son<s%> <S%G2228>or<s%> <S%G2364>daughter<s%> <S%G5228>more<s%> <S%G5228>than<s%> Me is not <S%G514>worthy<s%> of Me."},{"number":38,"verse":"\"And he <S%G3739>who<s%> does not <S%G2983>take<s%> his <S%G4716>cross<s%> and <S%G190>follow<s%> <S%G3694>after<s%> Me is not <S%G514>worthy<s%> of Me."},{"number":39,"verse":"\"He who has <S%G2147>found<s%> his <S%G5590>life<s%> shall <S%G622>lose<s%> it, and he who has <S%G622>lost<s%> his <S%G5590>life<s%> for My <S%G1752>sake<s%> shall <S%G2147>find<s%> it."},{"number":40,"verse":"\"He who <S%G1209>receives<s%> you <S%G1209>receives<s%> Me, and he who <S%G1209>receives<s%> Me <S%G1209>receives<s%> Him who <S%G649>sent<s%> Me."},{"number":41,"verse":"\"He who <S%G1209>receives<s%> a <S%G4396>prophet<s%> in [the] <S%G3686>name<s%> of a <S%G4396>prophet<s%> shall <S%G2983>receive<s%> a prophet's <S%G3408>reward;<s%> and he who <S%G1209>receives<s%> a <S%G1342>righteous<s%> <S%G1342>man<s%> in the <S%G3686>name<s%> of a <S%G1342>righteous<s%> <S%G1342>man<s%> shall <S%G2983>receive<s%> a <S%G1342>righteous<s%> man's <S%G3408>reward.<s%>"},{"number":42,"verse":"\"And <S%G3739>whoever<s%> <S%G1437><s%> in the <S%G3686>name<s%> of a <S%G3101>disciple<s%> <S%G4222>gives<s%> to <S%G1520>one<s%> of <S%G3778>these<s%> <S%G3398>little<s%> <S%G3398>ones<s%> <S%G3441>even<s%> a <S%G4221>cup<s%> of <S%G5593>cold<s%> water to <S%G4222>drink,<s%> <S%G281>truly<s%> I <S%G3004>say<s%> to you he shall not <S%G622>lose<s%> his <S%G3408>reward.<s%>\""}]}