{"bibleAbbr":"KJV1850+","bookName":"Ecclesiastes","bookEnglishName":"Ecclesiastes","chapterNumber":3,"verses":[{"number":1,"verse":"To every <S%H3605><s%> thing there is a season, <S%H2165><s%> and a time <S%H6256><s%> to every <S%H3605><s%> purpose <S%H2656><s%> under <S%H8478><s%> the heaven: <S%H8064><s%>"},{"number":2,"verse":"A time <S%H6256><s%> to be born, <S%H3205><s%> and a time <S%H6256><s%> to die; <S%H4191><s%> a time <S%H6256><s%> to plant, <S%H5193><s%> and a time <S%H6256><s%> to pluck up <S%H6131><s%> that which is planted; <S%H5193><s%>"},{"number":3,"verse":"A time <S%H6256><s%> to kill, <S%H2026><s%> and a time <S%H6256><s%> to heal; <S%H7495><s%> a time <S%H6256><s%> to break down, <S%H6555><s%> and a time <S%H6256><s%> to build up; <S%H1129><s%>"},{"number":4,"verse":"A time <S%H6256><s%> to weep, <S%H1058><s%> and a time <S%H6256><s%> to laugh; <S%H7832><s%> a time <S%H6256><s%> to mourn, <S%H5594><s%> and a time <S%H6256><s%> to dance; <S%H7540><s%>"},{"number":5,"verse":"A time <S%H6256><s%> to cast away <S%H7993><s%> stones, <S%H68><s%> and a time <S%H6256><s%> to gather stones together; <S%H3664><s%> <S%H68><s%> a time <S%H6256><s%> to embrace, <S%H2263><s%> and a time <S%H6256><s%> to refrain <S%H7368><s%> from embracing; <S%H4480><s%> <S%H2263><s%>"},{"number":6,"verse":"A time <S%H6256><s%> to get, <S%H1245><s%> and a time <S%H6256><s%> to lose; <S%H6><s%> a time <S%H6256><s%> to keep, <S%H8104><s%> and a time <S%H6256><s%> to cast away; <S%H7993><s%>"},{"number":7,"verse":"A time <S%H6256><s%> to rend, <S%H7167><s%> and a time <S%H6256><s%> to sew; <S%H8609><s%> a time <S%H6256><s%> to keep silence, <S%H2814><s%> and a time <S%H6256><s%> to speak; <S%H1696><s%>"},{"number":8,"verse":"A time <S%H6256><s%> to love, <S%H157><s%> and a time <S%H6256><s%> to hate; <S%H8130><s%> a time <S%H6256><s%> of war, <S%H4421><s%> and a time <S%H6256><s%> of peace. <S%H7965><s%>"},{"number":9,"verse":"What <S%H4100><s%> profit <S%H3504><s%> hath he that worketh <S%H6213><s%> in that wherein <S%H834><s%> he <S%H1931><s%> laboreth? <S%H6001><s%>"},{"number":10,"verse":"I have seen <S%H7200><s%> <S%H853><s%> the travail, <S%H6045><s%> which <S%H834><s%> God <S%H430><s%> hath given <S%H5414><s%> to the sons <S%H1121><s%> of men <S%H120><s%> to be exercised <S%H6031><s%> in it."},{"number":11,"verse":"He hath made <S%H6213><s%> <S%H853><s%> every <S%H3605><s%> thing beautiful <S%H3303><s%> in his time: <S%H6256><s%> also <S%H1571><s%> he hath set <S%H5414><s%> <S%H853><s%> the world <S%H5769><s%> in their heart, <S%H3820><s%> so that <S%H834><s%> no <S%H4480><s%> <S%H1097><s%> man <S%H120><s%> can find out <S%H4672><s%> <S%H853><s%> the work <S%H4639><s%> that <S%H834><s%> God <S%H430><s%> maketh <S%H6213><s%> from the beginning <S%H4480><s%> <S%H7218><s%> to <S%H5704><s%> the end. <S%H5490><s%>"},{"number":12,"verse":"I know <S%H3045><s%> that <S%H3588><s%> there is no <S%H369><s%> good <S%H2896><s%> in them, but <S%H518><s%> for <S%H3588><s%> a man to rejoice, <S%H8055><s%> and to do <S%H6213><s%> good <S%H2896><s%> in his life. <S%H2416><s%>"},{"number":13,"verse":"And also <S%H1571><s%> that every man should eat <S%H7945><s%> <S%H398><s%> <S%H3605><s%> <S%H120><s%> and drink, <S%H8354><s%> and enjoy <S%H7200><s%> the good <S%H2896><s%> of all <S%H3605><s%> his labor, <S%H5999><s%> it <S%H1931><s%> is the gift <S%H4991><s%> of God. <S%H430><s%>"},{"number":14,"verse":"I know <S%H3045><s%> that, <S%H3588><s%> whatsoever <S%H3605><s%> <S%H834><s%> God <S%H430><s%> doeth, <S%H6213><s%> it <S%H1931><s%> shall be <S%H1961><s%> forever: <S%H5769><s%> nothing <S%H369><s%> can be put <S%H3254><s%> to <S%H5921><s%> it, nor <S%H369><s%> any thing taken <S%H1639><s%> from <S%H4480><s%> it: and God <S%H430><s%> doeth <S%H6213><s%> it, that men should fear <S%H7945><s%> <S%H3372><s%> before <S%H4480><s%> <S%H6440><s%> him."},{"number":15,"verse":"That which hath been <S%H4100><s%> <S%H7945><s%> <S%H1961><s%> is now; <S%H3528><s%> and that <S%H1931><s%> which <S%H834><s%> is to be <S%H1961><s%> hath already <S%H3528><s%> been; <S%H1961><s%> and God <S%H430><s%> requireth <S%H1245><s%> <S%H853><s%> that which is past. <S%H7291><s%>"},{"number":16,"verse":"And moreover <S%H5750><s%> I saw <S%H7200><s%> under <S%H8478><s%> the sun <S%H8121><s%> the place <S%H4725><s%> of judgment, <S%H4941><s%> that wickedness <S%H7562><s%> was there; <S%H8033><s%> and the place <S%H4725><s%> of righteousness, <S%H6664><s%> that iniquity <S%H7562><s%> was there. <S%H8033><s%>"},{"number":17,"verse":"I <S%H589><s%> said <S%H559><s%> in mine heart, <S%H3820><s%> God <S%H430><s%> shall judge <S%H8199><s%> <S%H853><s%> the righteous <S%H6662><s%> and the wicked: <S%H7563><s%> for <S%H3588><s%> there is a time <S%H6256><s%> there <S%H8033><s%> for every <S%H3605><s%> purpose <S%H2656><s%> and for <S%H5921><s%> every <S%H3605><s%> work. <S%H4639><s%>"},{"number":18,"verse":"I <S%H589><s%> said <S%H559><s%> in mine heart <S%H3820><s%> concerning <S%H5921><s%> the estate <S%H1700><s%> of the sons <S%H1121><s%> of men, <S%H120><s%> that God <S%H430><s%> might manifest <S%H1305><s%> them, and that they <S%H1992><s%> might see <S%H7200><s%> that they <S%H7945><s%> themselves are beasts. <S%H929><s%>"},{"number":19,"verse":"For <S%H3588><s%> that which befalleth <S%H4745><s%> the sons <S%H1121><s%> of men <S%H120><s%> befalleth <S%H4745><s%> beasts; <S%H929><s%> even one thing <S%H259><s%> befalleth <S%H4745><s%> them: as the one <S%H2088><s%> dieth, <S%H4194><s%> so <S%H3651><s%> dieth <S%H4194><s%> the other; <S%H2088><s%> yea, they have all <S%H3605><s%> one <S%H259><s%> breath; <S%H7307><s%> so that a man <S%H120><s%> hath no <S%H369><s%> preeminence <S%H4195><s%> above <S%H4480><s%> a beast: <S%H929><s%> for <S%H3588><s%> all <S%H3605><s%> is vanity. <S%H1892><s%>"},{"number":20,"verse":"All <S%H3605><s%> go <S%H1980><s%> unto <S%H413><s%> one <S%H259><s%> place; <S%H4725><s%> all <S%H3605><s%> are <S%H1961><s%> of <S%H4480><s%> the dust, <S%H6083><s%> and all <S%H3605><s%> turn to dust again. <S%H7725><s%> <S%H413><s%> <S%H6083><s%>"},{"number":21,"verse":"Who <S%H4310><s%> knoweth <S%H3045><s%> the spirit <S%H7307><s%> of man <S%H120><s%> that <S%H1931><s%> goeth <S%H5927><s%> upward, <S%H4605><s%> and the spirit <S%H7307><s%> of the beast <S%H929><s%> that <S%H1931><s%> goeth <S%H3381><s%> downward <S%H4295><s%> to the earth? <S%H776><s%>"},{"number":22,"verse":"Wherefore I perceive <S%H7200><s%> that <S%H3588><s%> there is nothing <S%H369><s%> better, <S%H2896><s%> than that <S%H4480><s%> <S%H834><s%> a man <S%H120><s%> should rejoice <S%H8055><s%> in his own works; <S%H4639><s%> for <S%H3588><s%> that <S%H1931><s%> is his portion: <S%H2506><s%> for <S%H3588><s%> who <S%H4310><s%> shall bring <S%H935><s%> him to see <S%H7200><s%> what shall be <S%H4100><s%> <S%H7945><s%> <S%H1961><s%> after <S%H310><s%> him?"}]}