{"bibleAbbr":"NASB1995+","bookName":"Nahum","bookEnglishName":"Nahum","chapterNumber":2,"verses":[{"number":1,"verse":"The one <S%H4650><s%> who <S%H4650><s%> scatters <S%H4650><s%> has come <S%H5927><s%> up against <S%H5921><s%> you. Man <S%H5341><s%> the fortress, <S%H4694><s%> watch <S%H6822><s%> the road; <S%H1870><s%> Strengthen <S%H2388><s%> your back, <S%H4975><s%> summon <S%H553><s%> all <S%H3966><s%> [your] strength. <S%H3581><s%>"},{"number":2,"verse":"For the Lord <S%H3068><s%> will restore <S%H7725><s%> the splendor <S%H1347><s%> of Jacob <S%H3290><s%> Like the splendor <S%H1347><s%> of Israel, <S%H3478><s%> Even though <S%H3588><s%> devastators <S%H1238><s%> have devastated <S%H1238><s%> them And destroyed <S%H7843><s%> their vine <S%H2156><s%> branches. <S%H2156><s%>"},{"number":3,"verse":"The shields <S%H4043><s%> of his mighty <S%H1368><s%> men <S%H1368><s%> are [colored] red, <S%H119><s%> The warriors <S%H376><s%> <S%H2428><s%> are dressed <S%H8529><s%> in scarlet, <S%H8529><s%> The chariots <S%H7393><s%> are [enveloped] in flashing <S%H784><s%> steel <S%H6393><s%> When <S%H3117><s%> he is prepared <S%H3559><s%> [to march], And the cypress <S%H1265><s%> [spears] are brandished. <S%H7477><s%>"},{"number":4,"verse":"The chariots <S%H7393><s%> race <S%H1984><s%> madly <S%H1984><s%> in the streets, <S%H2351><s%> They rush <S%H8264><s%> wildly <S%H8264><s%> in the squares, <S%H7339><s%> Their appearance <S%H4758><s%> is like torches, <S%H3940><s%> They dash <S%H7323><s%> to and fro <S%H7323><s%> like lightning <S%H1300><s%> flashes. <S%H1300><s%>"},{"number":5,"verse":"He remembers <S%H2142><s%> his nobles; <S%H117><s%> They stumble <S%H3782><s%> in their march, <S%H1979><s%> They hurry <S%H4116><s%> to her wall, <S%H2346><s%> And the mantelet <S%H9361><s%> is set <S%H3559><s%> up."},{"number":6,"verse":"The gates <S%H8179><s%> of the rivers <S%H5104><s%> are opened, <S%H6605><s%> And the palace <S%H1964><s%> is dissolved. <S%H4127><s%>"},{"number":7,"verse":"And it is fixed: <S%H5324><s%> She is stripped, <S%H1540><s%> she is carried <S%H5927><s%> away, <S%H5927><s%> And her handmaids <S%H519><s%> are moaning <S%H9313><s%> like the sound <S%H6963><s%> of doves, <S%H3123><s%> Beating <S%H8608><s%> on their breasts. <S%H3824><s%>"},{"number":8,"verse":"Though Nineveh <S%H5210><s%> [was] like a pool <S%H1295><s%> of water <S%H4325><s%> throughout <S%H4480><s%> her days, <S%H3117><s%> Now they are fleeing; <S%H5127><s%> \"Stop, <S%H5975><s%> stop, <S%H5975><s%>\" But no <S%H369><s%> one <S%H369><s%> turns <S%H6437><s%> back. <S%H6437><s%>"},{"number":9,"verse":"Plunder <S%H962><s%> the silver! <S%H3701><s%> Plunder <S%H962><s%> the gold! <S%H2091><s%> For there <S%H369><s%> is no <S%H369><s%> limit <S%H9523><s%> to the treasure <S%H8499><s%> – Wealth <S%H9202><s%> from every <S%H3605><s%> kind of desirable <S%H2532><s%> object. <S%H3627><s%>"},{"number":10,"verse":"She is emptied! <S%H950><s%> Yes, she is desolate <S%H4003><s%> and waste! <S%H1110><s%> Hearts <S%H3820><s%> are melting <S%H4549><s%> and knees <S%H1290><s%> knocking! <S%H6375><s%> Also anguish <S%H2479><s%> is in the whole <S%H3605><s%> body, <S%H4975><s%> And all <S%H3605><s%> their faces <S%H6440><s%> are grown <S%H6908><s%> pale! <S%H6289><s%>"},{"number":11,"verse":"Where <S%H346><s%> is the den <S%H4583><s%> of the lions <S%H9030><s%> And the feeding <S%H4829><s%> place <S%H4829><s%> of the young <S%H3715><s%> lions, <S%H3715><s%> Where <S%H834><s%> <S%H8033><s%> the lion, <S%H9030><s%> lioness, <S%H3833><s%> and lion's cub <S%H1482><s%> prowled, <S%H1980><s%> With nothing <S%H369><s%> to disturb <S%H2729><s%> [them]?"},{"number":12,"verse":"The lion <S%H9030><s%> tore <S%H2963><s%> enough <S%H1767><s%> for his cubs, <S%H1484><s%> Killed <S%H2614><s%> [enough] for his lionesses, <S%H3833><s%> And filled <S%H4390><s%> his lairs <S%H2356><s%> with prey <S%H2964><s%> And his dens <S%H4585><s%> with torn <S%H2966><s%> flesh. <S%H2966><s%>"},{"number":13,"verse":"\"Behold, <S%H2009><s%> I am against <S%H413><s%> you,\" declares <S%H5002><s%> the Lord <S%H3068><s%> of hosts. <S%H6635><s%> \"I will burn <S%H1197><s%> up her chariots <S%H7393><s%> in smoke, <S%H6227><s%> a sword <S%H2719><s%> will devour <S%H398><s%> your young <S%H3715><s%> lions, <S%H3715><s%> I will cut <S%H3772><s%> off <S%H3772><s%> your prey <S%H2964><s%> from the land, <S%H776><s%> and no <S%H3808><s%> longer <S%H5750><s%> will the voice <S%H6963><s%> of your messengers <S%H4397><s%> be heard. <S%H8085><s%>\""}]}