{"bibleAbbr":"CVB1535","bookName":"Psalms","bookEnglishName":"Psalms","chapterNumber":33,"verses":[{"number":1,"verse":"Reioyse in ye LORDE (o ye rightuous) for it becommeth well the iust to be thankfull."},{"number":2,"verse":"Prayse the LORDE with harpe: synge psalmes vnto him with the lute and instrument of ten strynges."},{"number":3,"verse":"Singe him a new songe, yee synge lustely vnto him & with a good corage."},{"number":4,"verse":"For the worde of ye LORDE is true, and all his workes are faithfull."},{"number":5,"verse":"He loueth mercy & iudgment, ye earth is full of the goodnesse of the LORDE"},{"number":6,"verse":"By the worde of the LORDE were the heauens made, & all the hoostes of them by ye breth of his mouth."},{"number":7,"verse":"He gathereth ye waters together as it were in a bottell, & laieth vp the depe in secrete."},{"number":8,"verse":"Let all the earth feare the LORDE, and let all them that dwell in the worlde, stode in awe of him."},{"number":9,"verse":"For loke what he sayeth, it is done: and loke what he comaudeth, it stondeth fast."},{"number":10,"verse":"The LORDE bryngeth the councell of the Heithen to naught, and turneth the deuyces of the people."},{"number":11,"verse":"But the coucell of the LORDE endureth, and the thoughtes of his hert from generacion to generacion."},{"number":12,"verse":"Blessed are the people that holde the LORDE for their God, & blessed are the folke whom he hath chosen to be his heretage."},{"number":13,"verse":"The LORDE loketh downe from heauen, & beholdeth all the children of men:"},{"number":14,"verse":"from his stronge seate he considreth all them yt dwell in the worlde."},{"number":15,"verse":"He only hath fashioned all the hertes of them, & knoweth all their workes."},{"number":16,"verse":"A kynge is not helped by his owne greate hoost, nether is a giaunte saued thorow the might of his owne stregth."},{"number":17,"verse":"A horse is but a vayne thynge to saue a man, it is not the power of his stregth that can delyuer him."},{"number":18,"verse":"Beholde, the eye of the LORDE loketh vnto them that feare him, & put their trust in his mercy."},{"number":19,"verse":"That he maye delyuer their soules from death, and to fede them in the deare tyme."},{"number":20,"verse":"Let oure soule paciently abyde the LORDE, for he is oure helpe and shilde."},{"number":21,"verse":"So shal oure herte reioyse in him, because we haue hoped in his holy name."},{"number":22,"verse":"Let thy mercifull kyndnesse (o LORDE) be vpon vs, like as we put oure trust in the."}]}