{"bibleAbbr":"WHNU1881+","bookName":"Leviticus","bookEnglishName":"Leviticus","chapterNumber":4,"verses":[{"number":1,"verse":"ιησους <S%G2424><s%> δε <S%G1161><s%> πληρης <S%G4134><s%> πνευματος <S%G4151><s%> αγιου <S%G40><s%> υπεστρεψεν <S%G99999><s%> απο <S%G575><s%> του <S%G3588><s%> ιορδανου <S%G2446><s%> και <S%G2532><s%> ηγετο <S%G99999><s%> εν <S%G1722><s%> τω <S%G3588><s%> πνευματι <S%G4151><s%> εν <S%G1722><s%> τη <S%G3588><s%> ερημω <S%G2048><s%>"},{"number":2,"verse":"ημερας <S%G2250><s%> τεσσερακοντα <S%G5062><s%> πειραζομενος <S%G99999><s%> υπο <S%G5259><s%> του <S%G3588><s%> διαβολου <S%G1228><s%> και <S%G2532><s%> ουκ <S%G3756><s%> εφαγεν <S%G99999><s%> ουδεν <S%G3762><s%> εν <S%G1722><s%> ταις <S%G3588><s%> ημεραις <S%G2250><s%> εκειναις <S%G1565><s%> και <S%G2532><s%> συντελεσθεισων <S%G99999><s%> αυτων <S%G846><s%> επεινασεν <S%G99999><s%>"},{"number":3,"verse":"ειπεν <S%G99999><s%> δε <S%G1161><s%> αυτω <S%G846><s%> ο <S%G3588><s%> διαβολος <S%G1228><s%> ει <S%G1487><s%> υιος <S%G5207><s%> ει <S%G99999><s%> του <S%G3588><s%> θεου <S%G2316><s%> ειπε <S%G99999><s%> τω <S%G3588><s%> λιθω <S%G3037><s%> τουτω <S%G5129><s%> ινα <S%G2443><s%> γενηται <S%G99999><s%> αρτος <S%G740><s%>"},{"number":4,"verse":"και <S%G2532><s%> απεκριθη <S%G99999><s%> προς <S%G4314><s%> αυτον <S%G846><s%> ο <S%G3588><s%> ιησους <S%G2424><s%> γεγραπται <S%G99999><s%> οτι <S%G3754><s%> ουκ <S%G3756><s%> επ <S%G1909><s%> αρτω <S%G740><s%> μονω <S%G3441><s%> ζησεται <S%G99999><s%> ο <S%G3588><s%> ανθρωπος <S%G444><s%>"},{"number":5,"verse":"και <S%G2532><s%> αναγαγων <S%G99999><s%> αυτον <S%G846><s%> εδειξεν <S%G99999><s%> αυτω <S%G846><s%> πασας <S%G3956><s%> τας <S%G3588><s%> βασιλειας <S%G932><s%> της <S%G3588><s%> οικουμενης <S%G3625><s%> εν <S%G1722><s%> στιγμη <S%G4743><s%> χρονου <S%G5550><s%>"},{"number":6,"verse":"και <S%G2532><s%> ειπεν <S%G99999><s%> αυτω <S%G846><s%> ο <S%G3588><s%> διαβολος <S%G1228><s%> σοι <S%G4671><s%> δωσω <S%G99999><s%> την <S%G3588><s%> εξουσιαν <S%G1849><s%> ταυτην <S%G3778><s%> απασαν <S%G537><s%> και <S%G2532><s%> την <S%G3588><s%> δοξαν <S%G1391><s%> αυτων <S%G846><s%> οτι <S%G3754><s%> εμοι <S%G1698><s%> παραδεδοται <S%G99999><s%> και <S%G2532><s%> ω <S%G3739><s%> εαν <S%G1437><s%> θελω <S%G99999><s%> διδωμι <S%G99999><s%> αυτην <S%G846><s%>"},{"number":7,"verse":"συ <S%G4771><s%> ουν <S%G3767><s%> εαν <S%G1437><s%> προσκυνησης <S%G99999><s%> ενωπιον <S%G1799><s%> εμου <S%G1700><s%> εσται <S%G99999><s%> σου <S%G4675><s%> πασα <S%G3956><s%>"},{"number":8,"verse":"και <S%G2532><s%> αποκριθεις <S%G99999><s%> ο <S%G3588><s%> ιησους <S%G2424><s%> ειπεν <S%G99999><s%> αυτω <S%G846><s%> γεγραπται <S%G99999><s%> κυριον <S%G2962><s%> τον <S%G3588><s%> θεον <S%G2316><s%> σου <S%G4675><s%> προσκυνησεις <S%G99999><s%> και <S%G2532><s%> αυτω <S%G846><s%> μονω <S%G3441><s%> λατρευσεις <S%G99999><s%>"},{"number":9,"verse":"ηγαγεν <S%G99999><s%> δε <S%G1161><s%> αυτον <S%G846><s%> εις <S%G1519><s%> ιερουσαλημ <S%G2419><s%> και <S%G2532><s%> εστησεν <S%G99999><s%> επι <S%G1909><s%> το <S%G3588><s%> πτερυγιον <S%G4419><s%> του <S%G3588><s%> ιερου <S%G2411><s%> και <S%G2532><s%> ειπεν <S%G99999><s%> {VAR1: [αυτω] <S%G846><s%> } {VAR2: αυτω <S%G846><s%> } ει <S%G1487><s%> υιος <S%G5207><s%> ει <S%G99999><s%> του <S%G3588><s%> θεου <S%G2316><s%> βαλε <S%G99999><s%> σεαυτον <S%G4572><s%> εντευθεν <S%G1782><s%> κατω <S%G2736><s%>"},{"number":10,"verse":"γεγραπται <S%G99999><s%> γαρ <S%G1063><s%> οτι <S%G3754><s%> τοις <S%G3588><s%> αγγελοις <S%G32><s%> αυτου <S%G846><s%> εντελειται <S%G99999><s%> περι <S%G4012><s%> σου <S%G4675><s%> του <S%G3588><s%> διαφυλαξαι <S%G99999><s%> σε <S%G4571><s%>"},{"number":11,"verse":"και <S%G2532><s%> οτι <S%G3754><s%> επι <S%G1909><s%> χειρων <S%G5495><s%> αρουσιν <S%G99999><s%> σε <S%G4571><s%> μηποτε <S%G3379><s%> προσκοψης <S%G99999><s%> προς <S%G4314><s%> λιθον <S%G3037><s%> τον <S%G3588><s%> ποδα <S%G4228><s%> σου <S%G4675><s%>"},{"number":12,"verse":"και <S%G2532><s%> αποκριθεις <S%G99999><s%> ειπεν <S%G99999><s%> αυτω <S%G846><s%> ο <S%G3588><s%> ιησους <S%G2424><s%> οτι <S%G3754><s%> ειρηται <S%G99999><s%> ουκ <S%G3756><s%> εκπειρασεις <S%G99999><s%> κυριον <S%G2962><s%> τον <S%G3588><s%> θεον <S%G2316><s%> σου <S%G4675><s%>"},{"number":13,"verse":"και <S%G2532><s%> συντελεσας <S%G99999><s%> παντα <S%G3956><s%> πειρασμον <S%G3986><s%> ο <S%G3588><s%> διαβολος <S%G1228><s%> απεστη <S%G99999><s%> απ <S%G575><s%> αυτου <S%G846><s%> αχρι <S%G891><s%> καιρου <S%G2540><s%>"},{"number":14,"verse":"και <S%G2532><s%> υπεστρεψεν <S%G99999><s%> ο <S%G3588><s%> ιησους <S%G2424><s%> εν <S%G1722><s%> τη <S%G3588><s%> δυναμει <S%G1411><s%> του <S%G3588><s%> πνευματος <S%G4151><s%> εις <S%G1519><s%> την <S%G3588><s%> γαλιλαιαν <S%G1056><s%> και <S%G2532><s%> φημη <S%G5345><s%> εξηλθεν <S%G99999><s%> καθ <S%G2596><s%> ολης <S%G3650><s%> της <S%G3588><s%> περιχωρου <S%G4066><s%> περι <S%G4012><s%> αυτου <S%G846><s%>"},{"number":15,"verse":"και <S%G2532><s%> αυτος <S%G846><s%> εδιδασκεν <S%G99999><s%> εν <S%G1722><s%> ταις <S%G3588><s%> συναγωγαις <S%G4864><s%> αυτων <S%G846><s%> δοξαζομενος <S%G99999><s%> υπο <S%G5259><s%> παντων <S%G3956><s%>"},{"number":16,"verse":"και <S%G2532><s%> ηλθεν <S%G99999><s%> εις <S%G1519><s%> ναζαρα <S%G3478><s%> ου <S%G3757><s%> ην <S%G99999><s%> τεθραμμενος <S%G99999><s%> και <S%G2532><s%> εισηλθεν <S%G99999><s%> κατα <S%G2596><s%> το <S%G3588><s%> ειωθος <S%G99999><s%> αυτω <S%G846><s%> εν <S%G1722><s%> τη <S%G3588><s%> ημερα <S%G2250><s%> των <S%G3588><s%> σαββατων <S%G4521><s%> εις <S%G1519><s%> την <S%G3588><s%> συναγωγην <S%G4864><s%> και <S%G2532><s%> ανεστη <S%G99999><s%> αναγνωναι <S%G99999><s%>"},{"number":17,"verse":"και <S%G2532><s%> επεδοθη <S%G99999><s%> αυτω <S%G846><s%> βιβλιον <S%G975><s%> του <S%G3588><s%> προφητου <S%G4396><s%> ησαιου <S%G2268><s%> και <S%G2532><s%> {VAR1: ανοιξας <S%G99999><s%> } {VAR2: αναπτυξας <S%G99999><s%> } το <S%G3588><s%> βιβλιον <S%G975><s%> ευρεν <S%G99999><s%> {VAR1: [τον] <S%G3588><s%> } {VAR2: τον <S%G3588><s%> } τοπον <S%G5117><s%> ου <S%G3757><s%> ην <S%G99999><s%> γεγραμμενον <S%G99999><s%>"},{"number":18,"verse":"πνευμα <S%G4151><s%> κυριου <S%G2962><s%> επ <S%G1909><s%> εμε <S%G1691><s%> ου <S%G3739><s%> εινεκεν <S%G1752><s%> εχρισεν <S%G99999><s%> με <S%G3165><s%> ευαγγελισασθαι <S%G99999><s%> πτωχοις <S%G4434><s%> απεσταλκεν <S%G99999><s%> με <S%G3165><s%> κηρυξαι <S%G99999><s%> αιχμαλωτοις <S%G164><s%> αφεσιν <S%G859><s%> και <S%G2532><s%> τυφλοις <S%G5185><s%> αναβλεψιν <S%G309><s%> αποστειλαι <S%G99999><s%> τεθραυσμενους <S%G99999><s%> εν <S%G1722><s%> αφεσει <S%G859><s%>"},{"number":19,"verse":"κηρυξαι <S%G99999><s%> ενιαυτον <S%G1763><s%> κυριου <S%G2962><s%> δεκτον <S%G1184><s%>"},{"number":20,"verse":"και <S%G2532><s%> πτυξας <S%G99999><s%> το <S%G3588><s%> βιβλιον <S%G975><s%> αποδους <S%G99999><s%> τω <S%G3588><s%> υπηρετη <S%G5257><s%> εκαθισεν <S%G99999><s%> και <S%G2532><s%> παντων <S%G3956><s%> οι <S%G3588><s%> οφθαλμοι <S%G3788><s%> εν <S%G1722><s%> τη <S%G3588><s%> συναγωγη <S%G4864><s%> ησαν <S%G99999><s%> ατενιζοντες <S%G99999><s%> αυτω <S%G846><s%>"},{"number":21,"verse":"ηρξατο <S%G99999><s%> δε <S%G1161><s%> λεγειν <S%G99999><s%> προς <S%G4314><s%> αυτους <S%G846><s%> οτι <S%G3754><s%> σημερον <S%G4594><s%> πεπληρωται <S%G99999><s%> η <S%G3588><s%> γραφη <S%G1124><s%> αυτη <S%G3778><s%> εν <S%G1722><s%> τοις <S%G3588><s%> ωσιν <S%G3775><s%> υμων <S%G5216><s%>"},{"number":22,"verse":"και <S%G2532><s%> παντες <S%G3956><s%> εμαρτυρουν <S%G99999><s%> αυτω <S%G846><s%> και <S%G2532><s%> εθαυμαζον <S%G99999><s%> επι <S%G1909><s%> τοις <S%G3588><s%> λογοις <S%G3056><s%> της <S%G3588><s%> χαριτος <S%G5485><s%> τοις <S%G3588><s%> εκπορευομενοις <S%G99999><s%> εκ <S%G1537><s%> του <S%G3588><s%> στοματος <S%G4750><s%> αυτου <S%G846><s%> και <S%G2532><s%> ελεγον <S%G99999><s%> ουχι <S%G3780><s%> υιος <S%G5207><s%> εστιν <S%G99999><s%> ιωσηφ <S%G2501><s%> ουτος <S%G3778><s%>"},{"number":23,"verse":"και <S%G2532><s%> ειπεν <S%G99999><s%> προς <S%G4314><s%> αυτους <S%G846><s%> παντως <S%G3843><s%> ερειτε <S%G99999><s%> μοι <S%G3427><s%> την <S%G3588><s%> παραβολην <S%G3850><s%> ταυτην <S%G3778><s%> ιατρε <S%G2395><s%> θεραπευσον <S%G99999><s%> σεαυτον <S%G4572><s%> οσα <S%G3745><s%> ηκουσαμεν <S%G99999><s%> γενομενα <S%G99999><s%> εις <S%G1519><s%> την <S%G3588><s%> καφαρναουμ <S%G2584><s%> ποιησον <S%G99999><s%> και <S%G2532><s%> ωδε <S%G5602><s%> εν <S%G1722><s%> τη <S%G3588><s%> πατριδι <S%G3968><s%> σου <S%G4675><s%>"},{"number":24,"verse":"ειπεν <S%G99999><s%> δε <S%G1161><s%> αμην <S%G281><s%> λεγω <S%G99999><s%> υμιν <S%G5213><s%> οτι <S%G3754><s%> ουδεις <S%G3762><s%> προφητης <S%G4396><s%> δεκτος <S%G1184><s%> εστιν <S%G99999><s%> εν <S%G1722><s%> τη <S%G3588><s%> πατριδι <S%G3968><s%> αυτου <S%G846><s%>"},{"number":25,"verse":"επ <S%G1909><s%> αληθειας <S%G225><s%> δε <S%G1161><s%> λεγω <S%G99999><s%> υμιν <S%G5213><s%> πολλαι <S%G4183><s%> χηραι <S%G5503><s%> ησαν <S%G99999><s%> εν <S%G1722><s%> ταις <S%G3588><s%> ημεραις <S%G2250><s%> ηλιου <S%G2243><s%> εν <S%G1722><s%> τω <S%G3588><s%> ισραηλ <S%G2474><s%> οτε <S%G3753><s%> εκλεισθη <S%G99999><s%> ο <S%G3588><s%> ουρανος <S%G3772><s%> {VAR2: επι <S%G1909><s%> } ετη <S%G2094><s%> τρια <S%G5140><s%> και <S%G2532><s%> μηνας <S%G3376><s%> εξ <S%G1803><s%> ως <S%G5613><s%> εγενετο <S%G99999><s%> λιμος <S%G3042><s%> μεγας <S%G3173><s%> επι <S%G1909><s%> πασαν <S%G3956><s%> την <S%G3588><s%> γην <S%G1093><s%>"},{"number":26,"verse":"και <S%G2532><s%> προς <S%G4314><s%> ουδεμιαν <S%G3762><s%> αυτων <S%G846><s%> επεμφθη <S%G99999><s%> ηλιας <S%G2243><s%> ει <S%G1487><s%> μη <S%G3361><s%> εις <S%G1519><s%> σαρεπτα <S%G4558><s%> της <S%G3588><s%> σιδωνιας <S%G4606><s%> προς <S%G4314><s%> γυναικα <S%G1135><s%> χηραν <S%G5503><s%>"},{"number":27,"verse":"και <S%G2532><s%> πολλοι <S%G4183><s%> λεπροι <S%G3015><s%> ησαν <S%G99999><s%> εν <S%G1722><s%> τω <S%G3588><s%> ισραηλ <S%G2474><s%> επι <S%G1909><s%> ελισαιου <S%G1666><s%> του <S%G3588><s%> προφητου <S%G4396><s%> και <S%G2532><s%> ουδεις <S%G3762><s%> αυτων <S%G846><s%> εκαθαρισθη <S%G99999><s%> ει <S%G1487><s%> μη <S%G3361><s%> ναιμαν <S%G3497><s%> ο <S%G3588><s%> συρος <S%G4948><s%>"},{"number":28,"verse":"και <S%G2532><s%> επλησθησαν <S%G99999><s%> παντες <S%G3956><s%> θυμου <S%G2372><s%> εν <S%G1722><s%> τη <S%G3588><s%> συναγωγη <S%G4864><s%> ακουοντες <S%G99999><s%> ταυτα <S%G5023><s%>"},{"number":29,"verse":"και <S%G2532><s%> ανασταντες <S%G99999><s%> εξεβαλον <S%G99999><s%> αυτον <S%G846><s%> εξω <S%G1854><s%> της <S%G3588><s%> πολεως <S%G4172><s%> και <S%G2532><s%> ηγαγον <S%G99999><s%> αυτον <S%G846><s%> εως <S%G2193><s%> οφρυος <S%G3790><s%> του <S%G3588><s%> ορους <S%G3735><s%> εφ <S%G1909><s%> ου <S%G3739><s%> η <S%G3588><s%> πολις <S%G4172><s%> ωκοδομητο <S%G99999><s%> αυτων <S%G846><s%> ωστε <S%G5620><s%> κατακρημνισαι <S%G99999><s%> αυτον <S%G846><s%>"},{"number":30,"verse":"αυτος <S%G846><s%> δε <S%G1161><s%> διελθων <S%G99999><s%> δια <S%G1223><s%> μεσου <S%G3319><s%> αυτων <S%G846><s%> επορευετο <S%G99999><s%>"},{"number":31,"verse":"και <S%G2532><s%> κατηλθεν <S%G99999><s%> εις <S%G1519><s%> καφαρναουμ <S%G2584><s%> πολιν <S%G4172><s%> της <S%G3588><s%> γαλιλαιας <S%G1056><s%> και <S%G2532><s%> ην <S%G99999><s%> διδασκων <S%G99999><s%> αυτους <S%G846><s%> εν <S%G1722><s%> τοις <S%G3588><s%> σαββασιν <S%G4521><s%>"},{"number":32,"verse":"και <S%G2532><s%> εξεπλησσοντο <S%G99999><s%> επι <S%G1909><s%> τη <S%G3588><s%> διδαχη <S%G1322><s%> αυτου <S%G846><s%> οτι <S%G3754><s%> εν <S%G1722><s%> εξουσια <S%G1849><s%> ην <S%G99999><s%> ο <S%G3588><s%> λογος <S%G3056><s%> αυτου <S%G846><s%>"},{"number":33,"verse":"και <S%G2532><s%> εν <S%G1722><s%> τη <S%G3588><s%> συναγωγη <S%G4864><s%> ην <S%G99999><s%> ανθρωπος <S%G444><s%> εχων <S%G99999><s%> πνευμα <S%G4151><s%> δαιμονιου <S%G1140><s%> ακαθαρτου <S%G169><s%> και <S%G2532><s%> ανεκραξεν <S%G99999><s%> φωνη <S%G5456><s%> μεγαλη <S%G3173><s%>"},{"number":34,"verse":"εα <S%G1436><s%> τι <S%G5101><s%> ημιν <S%G2254><s%> και <S%G2532><s%> σοι <S%G4671><s%> ιησου <S%G2424><s%> ναζαρηνε <S%G3479><s%> ηλθες <S%G99999><s%> απολεσαι <S%G99999><s%> ημας <S%G2248><s%> οιδα <S%G99999><s%> σε <S%G4571><s%> τις <S%G5101><s%> ει <S%G99999><s%> ο <S%G3588><s%> αγιος <S%G40><s%> του <S%G3588><s%> θεου <S%G2316><s%>"},{"number":35,"verse":"και <S%G2532><s%> επετιμησεν <S%G99999><s%> αυτω <S%G846><s%> ο <S%G3588><s%> ιησους <S%G2424><s%> λεγων <S%G99999><s%> φιμωθητι <S%G99999><s%> και <S%G2532><s%> εξελθε <S%G99999><s%> απ <S%G575><s%> αυτου <S%G846><s%> και <S%G2532><s%> ριψαν <S%G99999><s%> αυτον <S%G846><s%> το <S%G3588><s%> δαιμονιον <S%G1140><s%> εις <S%G1519><s%> το <S%G3588><s%> μεσον <S%G3319><s%> εξηλθεν <S%G99999><s%> απ <S%G575><s%> αυτου <S%G846><s%> μηδεν <S%G3367><s%> βλαψαν <S%G99999><s%> αυτον <S%G846><s%>"},{"number":36,"verse":"και <S%G2532><s%> εγενετο <S%G99999><s%> θαμβος <S%G2285><s%> επι <S%G1909><s%> παντας <S%G3956><s%> και <S%G2532><s%> συνελαλουν <S%G99999><s%> προς <S%G4314><s%> αλληλους <S%G240><s%> λεγοντες <S%G99999><s%> τις <S%G5101><s%> ο <S%G3588><s%> λογος <S%G3056><s%> ουτος <S%G3778><s%> οτι <S%G3754><s%> εν <S%G1722><s%> εξουσια <S%G1849><s%> και <S%G2532><s%> δυναμει <S%G1411><s%> επιτασσει <S%G99999><s%> τοις <S%G3588><s%> ακαθαρτοις <S%G169><s%> πνευμασιν <S%G4151><s%> και <S%G2532><s%> εξερχονται <S%G99999><s%>"},{"number":37,"verse":"και <S%G2532><s%> εξεπορευετο <S%G99999><s%> ηχος <S%G2279><s%> περι <S%G4012><s%> αυτου <S%G846><s%> εις <S%G1519><s%> παντα <S%G3956><s%> τοπον <S%G5117><s%> της <S%G3588><s%> περιχωρου <S%G4066><s%>"},{"number":38,"verse":"αναστας <S%G99999><s%> δε <S%G1161><s%> απο <S%G575><s%> της <S%G3588><s%> συναγωγης <S%G4864><s%> εισηλθεν <S%G99999><s%> εις <S%G1519><s%> την <S%G3588><s%> οικιαν <S%G3614><s%> σιμωνος <S%G4613><s%> πενθερα <S%G3994><s%> δε <S%G1161><s%> του <S%G3588><s%> σιμωνος <S%G4613><s%> ην <S%G99999><s%> συνεχομενη <S%G99999><s%> πυρετω <S%G4446><s%> μεγαλω <S%G3173><s%> και <S%G2532><s%> ηρωτησαν <S%G99999><s%> αυτον <S%G846><s%> περι <S%G4012><s%> αυτης <S%G846><s%>"},{"number":39,"verse":"και <S%G2532><s%> επιστας <S%G99999><s%> επανω <S%G1883><s%> αυτης <S%G846><s%> επετιμησεν <S%G99999><s%> τω <S%G3588><s%> πυρετω <S%G4446><s%> και <S%G2532><s%> αφηκεν <S%G99999><s%> αυτην <S%G846><s%> παραχρημα <S%G3916><s%> δε <S%G1161><s%> αναστασα <S%G99999><s%> διηκονει <S%G99999><s%> αυτοις <S%G846><s%>"},{"number":40,"verse":"δυνοντος <S%G99999><s%> δε <S%G1161><s%> του <S%G3588><s%> ηλιου <S%G2246><s%> απαντες <S%G537><s%> οσοι <S%G3745><s%> ειχον <S%G99999><s%> ασθενουντας <S%G99999><s%> νοσοις <S%G3554><s%> ποικιλαις <S%G4164><s%> ηγαγον <S%G99999><s%> αυτους <S%G846><s%> προς <S%G4314><s%> αυτον <S%G846><s%> ο <S%G3588><s%> δε <S%G1161><s%> ενι <S%G1520><s%> εκαστω <S%G1538><s%> αυτων <S%G846><s%> τας <S%G3588><s%> χειρας <S%G5495><s%> επιτιθεις <S%G99999><s%> εθεραπευεν <S%G99999><s%> αυτους <S%G846><s%>"},{"number":41,"verse":"εξηρχετο <S%G99999><s%> δε <S%G1161><s%> και <S%G2532><s%> δαιμονια <S%G1140><s%> απο <S%G575><s%> πολλων <S%G4183><s%> {VAR1: κραζοντα <S%G99999><s%> } {VAR2: <κραυγαζοντα> <S%G99999><s%> } και <S%G2532><s%> λεγοντα <S%G99999><s%> οτι <S%G3754><s%> συ <S%G4771><s%> ει <S%G99999><s%> ο <S%G3588><s%> υιος <S%G5207><s%> του <S%G3588><s%> θεου <S%G2316><s%> και <S%G2532><s%> επιτιμων <S%G99999><s%> ουκ <S%G3756><s%> εια <S%G99999><s%> αυτα <S%G846><s%> λαλειν <S%G99999><s%> οτι <S%G3754><s%> ηδεισαν <S%G99999><s%> τον <S%G3588><s%> χριστον <S%G5547><s%> αυτον <S%G846><s%> ειναι <S%G99999><s%>"},{"number":42,"verse":"γενομενης <S%G99999><s%> δε <S%G1161><s%> ημερας <S%G2250><s%> εξελθων <S%G99999><s%> επορευθη <S%G99999><s%> εις <S%G1519><s%> ερημον <S%G2048><s%> τοπον <S%G5117><s%> και <S%G2532><s%> οι <S%G3588><s%> οχλοι <S%G3793><s%> επεζητουν <S%G99999><s%> αυτον <S%G846><s%> και <S%G2532><s%> ηλθον <S%G99999><s%> εως <S%G2193><s%> αυτου <S%G846><s%> και <S%G2532><s%> κατειχον <S%G99999><s%> αυτον <S%G846><s%> του <S%G3588><s%> μη <S%G3361><s%> πορευεσθαι <S%G99999><s%> απ <S%G575><s%> αυτων <S%G846><s%>"},{"number":43,"verse":"ο <S%G3588><s%> δε <S%G1161><s%> ειπεν <S%G99999><s%> προς <S%G4314><s%> αυτους <S%G846><s%> οτι <S%G3754><s%> και <S%G2532><s%> ταις <S%G3588><s%> ετεραις <S%G2087><s%> πολεσιν <S%G4172><s%> ευαγγελισασθαι <S%G99999><s%> με <S%G3165><s%> δει <S%G99999><s%> την <S%G3588><s%> βασιλειαν <S%G932><s%> του <S%G3588><s%> θεου <S%G2316><s%> οτι <S%G3754><s%> επι <S%G1909><s%> τουτο <S%G5124><s%> απεσταλην <S%G99999><s%>"},{"number":44,"verse":"και <S%G2532><s%> ην <S%G99999><s%> κηρυσσων <S%G99999><s%> εις <S%G1519><s%> τας <S%G3588><s%> συναγωγας <S%G4864><s%> της <S%G3588><s%> ιουδαιας <S%G2449><s%>"}]}